Metadata-Version: 1.0
Name: ny-probability
Version: 0.1
Summary: Gaussian and Binomial distributions
Home-page: UNKNOWN
Author: Nagarjuna Yegavinti
Author-email: yegavintin@gmail.com
License: UNKNOWN
Platform: UNKNOWN
